pytomaton
