Metadata-Version: 1.0
Name: pytomaton
Version: 1.1.1
Summary: A more convenient and succinct way of expressing state machines in Python
Home-page: https://github.com/haldean/pytomaton
Author: Will Haldean Brown
Author-email: will.h.brown@gmail.com
License: MIT
Keywords: automaton state machine library
Platform: UNKNOWN
Classifier: Development Status :: 4 - Beta
Classifier: Intended Audience :: Developers
Classifier: License :: OSI Approved :: MIT License
Classifier: Operating System :: OS Independent
Classifier: Programming Language :: Python :: 2.7
Classifier: Programming Language :: Python :: 3
Classifier: Topic :: Software Development :: Libraries
